examples/__init__.py
examples/geohash_to_geojson.py
examples/geojson_to_geohash.py
examples/shapefile_to_geohash.py
geohash_generator/__init__.py
geohash_generator/config.py
geohash_generator/geohash_generator.py
geohash_generator/geohash_util.py
geohash_generator/version.py
tests/__init__.py
tests/unit/__init__.py
tests/unit/test_geohash_util.py
geohash_generator-0.1.0.dist-info/LICENSE
geohash_generator-0.1.0.dist-info/METADATA
geohash_generator-0.1.0.dist-info/WHEEL
geohash_generator-0.1.0.dist-info/top_level.txt
geohash_generator-0.1.0.dist-info/RECORD
