Metadata-Version: 2.1
Name: geohash-generator
Version: 0.1.0
Summary: Geohash Generator is a python module that provides function for converting geojson and shapefile to geohash.
Home-page: https://github.com/Helfi-Pangestu-Labs/geohash-generator/
Download-URL: https://github.com/Helfi-Pangestu-Labs/geohash-generator/archive/main.tar.gz
Author: Helfi Pangestu
Author-email: hellfipangestu@gmail.com
License: MIT
Keywords: geohash,geojson,convert,geohash-generator,shapefile converter,geojson converter
Classifier: Development Status :: 5 - Production/Stable
Classifier: Intended Audience :: Developers
Classifier: Topic :: Software Development :: Build Tools
Classifier: License :: OSI Approved :: MIT License
Classifier: Natural Language :: English
Classifier: Programming Language :: Python :: 3
Classifier: Programming Language :: Python :: 3.4
Classifier: Programming Language :: Python :: 3.5
Classifier: Programming Language :: Python :: 3.6
Classifier: Programming Language :: Python :: 3.7
Classifier: Programming Language :: Python :: 3.8
Classifier: Programming Language :: Python :: 3.9
License-File: LICENSE
Requires-Dist: polygon-geohasher ==0.0.1
Requires-Dist: shapely ==1.8.5.post1
Requires-Dist: Geohash ==1.0
Requires-Dist: georaptor ==2.0.3
Requires-Dist: pyshp ==2.3.1
Requires-Dist: geojson ==2.5.0
Requires-Dist: geohashlite ==0.3.2
Requires-Dist: numpy ==1.23.4
